relap_py/__init__.py
relap_py/config.py
relap_py/main.py
scdap_adrian/__init__.py
scdap_adrian/config.py
scdap_adrian/main.py
relap_py-2.0.16.dist-info/LICENSE.txt
relap_py-2.0.16.dist-info/METADATA
relap_py-2.0.16.dist-info/WHEEL
relap_py-2.0.16.dist-info/top_level.txt
relap_py-2.0.16.dist-info/RECORD
