Metadata-Version: 2.1
Name: relap-py
Version: 2.0.16
Summary: Module for RELAP post-processing
Author: Jordi Freixa
Author-email: <jordi.freixa-terradas@upc.edu>
License: MIT
Keywords: relap,trace
License-File: LICENSE.txt
